{
  "required": true,
  "minVersion": "0.8",
  "package": "com.unascribed.yttr.mixin",
  "compatibilityLevel": "JAVA_8",
  "refmap": "yttr-refmap.json",
  "mixins": [
  	"void_fluid.MixinEntity",
	"squeeze_trees.MixinChunkGenerator",
	"aware_hopper.MixinCraftingResultSlot",
	"snare.MixinRecipeManager",
	"snare.MixinIngredient",
	"cleaver.MixinEnchantmentTargets",
	"cleaver.MixinMobEntity",
	"glowing_gas.MixinGlassBottleItem",
	"glowing_gas.MixinPistonHandler",
	"delicace.MixinHungerManager",
	"delicace.MixinLivingEntity",
	"crafting_sound.MixinCraftingRecipeSerializers",
	"crafting_sound.MixinCraftingResultSlot",
	"unbreakable_smithing.MixinSmithingScreenHandler",
	"accessor.AccessorLivingEntity",
	"accessor.AccessorStatusEffectInstance",
	"accessor.AccessorMobEntity",
	"accessor.AccessorShapedRecipe",
	"accessor.AccessorEntity",
	"accessor.AccessorDyeColor",
	"accessor.AccessorHorseBaseEntity"
  ],
  "client": [
  	"void_fluid.client.MixinGameRenderer",
	"rifle.client.MixinClientPlayNetworkHandler",
	"rifle.client.MixinMinecraftClient",
	"rifle.client.MixinPlayerEntityRenderer",
	"tooltip.client.MixinItemStack",
	"accessor.client.AccessorEntityRendererDispatcher",
	"accessor.client.AccessorEntityTrackingSoundInstance",
	"accessor.client.AccessorRenderPhase"
  ],
  "injectors": {
    "defaultRequire": 1
  }
}
